phasor_point_cli/__init__.py
phasor_point_cli/__main__.py
phasor_point_cli/_version.py
phasor_point_cli/argument_parser.py
phasor_point_cli/banner.py
phasor_point_cli/chunk_strategy.py
phasor_point_cli/cli.py
phasor_point_cli/command_router.py
phasor_point_cli/config.py
phasor_point_cli/config_paths.py
phasor_point_cli/connection_manager.py
phasor_point_cli/connection_pool.py
phasor_point_cli/constants.py
phasor_point_cli/data_extractor.py
phasor_point_cli/data_file_writer.py
phasor_point_cli/data_processor.py
phasor_point_cli/data_validator.py
phasor_point_cli/date_utils.py
phasor_point_cli/extraction_history.py
phasor_point_cli/extraction_manager.py
phasor_point_cli/file_utils.py
phasor_point_cli/models.py
phasor_point_cli/pmu_metadata.py
phasor_point_cli/power_calculator.py
phasor_point_cli/progress_tracker.py
phasor_point_cli/query_executor.py
phasor_point_cli/signal_handler.py
phasor_point_cli/spinner.py
phasor_point_cli/table_manager.py
phasor_point_cli/user_output.py
phasor_point_cli-0.5.2.dist-info/licenses/LICENSE
phasor_point_cli-0.5.2.dist-info/METADATA
phasor_point_cli-0.5.2.dist-info/WHEEL
phasor_point_cli-0.5.2.dist-info/entry_points.txt
phasor_point_cli-0.5.2.dist-info/top_level.txt
phasor_point_cli-0.5.2.dist-info/RECORD
