Metadata-Version: 2.4
Name: phasor-point-cli
Version: 0.5.2
Summary: A comprehensive CLI for extracting, processing, and analyzing PMU data from PhasorPoint databases
Author-email: Frederik Fast <ffb@energinet.dk>
License: Apache-2.0
Project-URL: Homepage, https://github.com/energinet-ti/phasor-point-cli
Project-URL: Documentation, https://github.com/energinet-ti/phasor-point-cli/blob/main/README.md
Project-URL: Repository, https://github.com/energinet-ti/phasor-point-cli
Project-URL: Issues, https://github.com/energinet-ti/phasor-point-cli/issues
Keywords: pmu,phasor,power-systems,data-extraction,cli
Classifier: Development Status :: 5 - Production/Stable
Classifier: Environment :: Console
Classifier: Intended Audience :: Science/Research
Classifier: Operating System :: OS Independent
Classifier: Programming Language :: Python :: 3
Classifier: Programming Language :: Python :: 3.8
Classifier: Programming Language :: Python :: 3.9
Classifier: Programming Language :: Python :: 3.10
Classifier: Programming Language :: Python :: 3.11
Classifier: Programming Language :: Python :: 3.12
Classifier: Topic :: Scientific/Engineering
Classifier: Topic :: Utilities
Requires-Python: >=3.8
License-File: LICENSE
Requires-Dist: numpy
Requires-Dist: pandas
Requires-Dist: pyarrow
Requires-Dist: pyodbc
Requires-Dist: python-dotenv
Requires-Dist: pytz
Requires-Dist: tzlocal
Provides-Extra: dev
Requires-Dist: pytest>=7.4.0; extra == "dev"
Requires-Dist: pytest-cov>=4.1.0; extra == "dev"
Requires-Dist: pytest-mock>=3.11.1; extra == "dev"
Requires-Dist: freezegun>=1.2.2; extra == "dev"
Requires-Dist: ruff>=0.1.0; extra == "dev"
Requires-Dist: pyright>=1.1.0; extra == "dev"
Requires-Dist: build>=0.10.0; extra == "dev"
Requires-Dist: setuptools-scm>=8.0; extra == "dev"
Requires-Dist: validate-pyproject>=0.15; extra == "dev"
Requires-Dist: cyclonedx-bom>=4.0.0; extra == "dev"
Dynamic: license-file
